django_email_verification/__init__.py
django_email_verification/apps.py
django_email_verification/confirm.py
django_email_verification/errors.py
django_email_verification/token_utils.py
django_email_verification/urls.py
django_email_verification/views.py
django_email_verification-0.3.3.dist-info/LICENSE
django_email_verification-0.3.3.dist-info/METADATA
django_email_verification-0.3.3.dist-info/WHEEL
django_email_verification-0.3.3.dist-info/top_level.txt
django_email_verification-0.3.3.dist-info/RECORD
