Metadata-Version: 2.1
Name: django-email-verification
Version: 0.3.3
Summary: Email confirmation app for django
Home-page: https://github.com/LeoneBacciu/django-email-verification
Author: Leone Bacciu
Author-email: leonebacciu@gmail.com
License: MIT
Classifier: Environment :: Web Environment
Classifier: Framework :: Django
Classifier: Intended Audience :: Developers
Classifier: Programming Language :: Python
Classifier: License :: OSI Approved :: MIT License
Classifier: Operating System :: OS Independent
Requires-Python: >=3.8
License-File: LICENSE
